tinypkg/__init__.py
tinypkg/_version.py
tinypkg/hi.py
tinypkg-0.0.4.dist-info/LICENSE.txt
tinypkg-0.0.4.dist-info/METADATA
tinypkg-0.0.4.dist-info/WHEEL
tinypkg-0.0.4.dist-info/top_level.txt
tinypkg-0.0.4.dist-info/RECORD
