Metadata-Version: 2.1
Name: tinypkg
Version: 0.0.4
Summary: a tiny package example w/setuptools
Home-page: https://github.com/denkiwakame/py-tiny-pkg
Author: denkiwakame
Author-email: denkivvakame@gmail.com
Maintainer: denkiwakame
Maintainer-email: denkivvakame@gmail.com
License: MIT License        
Project-URL: Homepage, https://github.com/denkiwakame/py-tiny-pkg
Project-URL: documentation, https://github.com/denkiwakame/py-tiny-pkg
Project-URL: repository, https://github.com/denkiwakame/py-tiny-pkg
Project-URL: changelog, https://github.com/denkiwakame/py-tiny-pkg/blob/main/CHANGELOG.md
Keywords: package,setuptools
Platform: UNKNOWN
Classifier: License :: OSI Approved :: MIT License
Classifier: Programming Language :: Python
Requires-Python: >=3.7
License-File: LICENSE.txt
Requires-Dist: requests
Provides-Extra: dev
Requires-Dist: pytest (==5.0.0) ; extra == 'dev'
Requires-Dist: pytest-cov[all] ; extra == 'dev'
Requires-Dist: mypy (==0.910) ; extra == 'dev'
Requires-Dist: black (==21.10b0) ; extra == 'dev'
